LICENSE
MANIFEST.in
README.rst
setup.py
linkdump/__init__.py
linkdump/admin.py
linkdump/models.py
linkdump/urls.py
linkdump/views.py
linkdump/templates/linkdump/list.html
linkdump/templates/linkdump/tag_list.html
linkdump/templates/linkdump/includes/dumps_panel.html
linkdump/templatetags/__init__.py
linkdump/templatetags/linkdump_filters.py
linkdump/templatetags/linkdump_tags.py
mezzanine_linkdump.egg-info/PKG-INFO
mezzanine_linkdump.egg-info/SOURCES.txt
mezzanine_linkdump.egg-info/dependency_links.txt
mezzanine_linkdump.egg-info/requires.txt
mezzanine_linkdump.egg-info/top_level.txt