Metadata-Version: 1.1
Name: mezzanine-linkdump
Version: 1.0.0
Summary: A Mezzanine app to create, display, and track links.
Home-page: http://github.com/prikhi/mezzanine-linkdump
Author: Pavan Rikhi
Author-email: pavan@sleepanarchy.com
License: GPLv3
Platform: UNKNOWN
Classifier: Development Status :: 5 - Production/Stable
Classifier: Environment :: Web Environment
Classifier: Framework :: Django
Classifier: Intended Audience :: Developers
Classifier: License :: OSI Approved :: GNU General Public License v3 (GPLv3)
Classifier: Operating System :: OS Independent
Classifier: Programming Language :: Python
Classifier: Topic :: Internet :: WWW/HTTP
